altitude_analysis/__init__.py
altitude_analysis/altitude_a.c
altitude_analysis/altitude_a.cpython-312-x86_64-linux-gnu.so
altitude_analysis-66.0.666.dist-info/METADATA
altitude_analysis-66.0.666.dist-info/WHEEL
altitude_analysis-66.0.666.dist-info/entry_points.txt
altitude_analysis-66.0.666.dist-info/top_level.txt
altitude_analysis-66.0.666.dist-info/RECORD
altitude_analysis-66.0.666.dist-info/licenses/LICENSE
