Metadata-Version: 2.1
Name: altitude-analysis
Version: 66.0.666
Summary: Advanced aircraft altitude analysis
Author: tokifyko
Classifier: Programming Language :: Python :: 3
Classifier: License :: OSI Approved :: MIT License
Classifier: Operating System :: OS Independent
Classifier: Intended Audience :: Science/Research
Classifier: Topic :: Scientific/Engineering
Requires-Python: >=3.8
License-File: LICENSE
Requires-Dist: certifi==2025.7.9
Requires-Dist: charset-normalizer==3.4.2
Requires-Dist: idna==3.10
Requires-Dist: joblib==1.5.1
Requires-Dist: numpy==2.3.1
Requires-Dist: pandas==2.3.1
Requires-Dist: python-dateutil==2.9.0.post0
Requires-Dist: pytz==2025.2
Requires-Dist: requests==2.32.4
Requires-Dist: scikit-learn==1.7.0
Requires-Dist: scipy==1.16.0
Requires-Dist: six==1.17.0
Requires-Dist: threadpoolctl==3.6.0
Requires-Dist: tzdata==2025.2
Requires-Dist: urllib3==2.5.0
